pgn2fixture/__init__.py
pgn2fixture/pgn2fixture.py
pgn2fixture/utils.py
pgn2fixture-1.0.4.dist-info/LICENSE
pgn2fixture-1.0.4.dist-info/METADATA
pgn2fixture-1.0.4.dist-info/WHEEL
pgn2fixture-1.0.4.dist-info/top_level.txt
pgn2fixture-1.0.4.dist-info/RECORD
