Metadata-Version: 2.1
Name: pgn2fixture
Version: 1.0.4
Summary: A very simple PGN to Django fixture converter.
Home-page: https://josias-alvarado.me
Author: Josias Alvarado
Author-email: josiasjag@gmail.com
License: MIT
Classifier: License :: OSI Approved :: MIT License
Classifier: Programming Language :: Python :: 3.3
Classifier: Programming Language :: Python :: 3.4
Classifier: Programming Language :: Python :: 3.5
Classifier: Programming Language :: Python :: 3.6
Classifier: Programming Language :: Python :: 3.7
Classifier: Programming Language :: Python :: 3.8
Classifier: Operating System :: OS Independent
Classifier: Topic :: Software Development
Classifier: Topic :: Games/Entertainment :: Board Games
Classifier: Intended Audience :: Developers
Classifier: Development Status :: 3 - Alpha
License-File: LICENSE
